tvmcli/__init__.py
tvmcli/__main__.py
tvmcli/compiler.py
tvmcli/frontends.py
tvmcli/main.py
tvmcli/model.py
tvmcli/pass_config.py
tvmcli/pass_list.py
tvmcli/runner.py
tvmcli/shape_parser.py
tvmcli/target.py
tvmcli/test.py
tvmcli/tunner.py
tvmcli-0.1.0.dist-info/METADATA
tvmcli-0.1.0.dist-info/WHEEL
tvmcli-0.1.0.dist-info/top_level.txt
tvmcli-0.1.0.dist-info/RECORD
