Metadata-Version: 2.1
Name: tvmcli
Version: 0.1.0
Summary: A Command Line Interface for TVM auto-scheduler, likely tvmc
Home-page: https://github.com/Tonylycxx/tvm-cmd
Author: Tony Liu
Author-email: 2290549567@qq.com
License: UNKNOWN
Platform: UNKNOWN
Classifier: Programming Language :: Python :: 3
Classifier: License :: OSI Approved :: MIT License
Classifier: Operating System :: OS Independent
